mtnmomoapi/__init__.py
mtnmomoapi/collection.py
mtnmomoapi/disbursement.py
mtnmomoapi-0.0.6.dist-info/LICENSE.txt
mtnmomoapi-0.0.6.dist-info/METADATA
mtnmomoapi-0.0.6.dist-info/WHEEL
mtnmomoapi-0.0.6.dist-info/top_level.txt
mtnmomoapi-0.0.6.dist-info/RECORD
