Metadata-Version: 2.1
Name: mtnmomoapi
Version: 0.0.6
Summary: An easy to use Python wrapper for the MTN MoMo API.
Home-page: https://github.com/sikaili99/mtnmomoapi
Author: Mathews Musukuma
Author-email: sikaili99@gmail.com
License: MIT license
Project-URL: Bug Tracker, https://github.com/sikaili99/mtnmomoapi/issues
Project-URL: repository, https://github.com/sikaili99/mtnmomoapi
Keywords: MoMo API,MoMo API Python Wrapper,MoMo API Python,MTN Zambia MoMO API Python,MTN Mobile Money API Python
Classifier: Programming Language :: Python :: 3
Classifier: License :: OSI Approved :: MIT License
Classifier: Operating System :: OS Independent
Requires-Python: >=3.6
License-File: LICENSE.txt
